{
  "configVersion": 1,
  "timestamp": 1781277490604,
  "index": "/index.html",
  "assetGroups": [
    {
      "name": "app",
      "installMode": "prefetch",
      "updateMode": "prefetch",
      "cacheQueryOptions": {
        "ignoreVary": true
      },
      "urls": [
        "/chunk-BTqFL-W6.js",
        "/chunk-BkuTk0YZ.js",
        "/chunk-Bootd70g.js",
        "/chunk-C0_8OVSk.js",
        "/chunk-C0bSLCE5.js",
        "/chunk-C8VUx5tz.js",
        "/chunk-C9JAyV3O.js",
        "/chunk-CZijNNNV.js",
        "/chunk-CazVxgio.js",
        "/chunk-Cn5-OQAh.js",
        "/chunk-CpJtyA6b.js",
        "/chunk-CqoeM8zE.js",
        "/chunk-CsXf57FG.js",
        "/chunk-Cx73aAe6.js",
        "/chunk-Cz3iYWRY.js",
        "/chunk-DG5sq5fk.js",
        "/chunk-DPXY-fVQ.js",
        "/chunk-Dfp82Ogv.js",
        "/chunk-Dta_GJj0.js",
        "/chunk-HUV4_jLT.js",
        "/chunk-Khg8wsls.js",
        "/chunk-PzpOrqc7.js",
        "/chunk-fyBPlGZN.js",
        "/chunk-kzr3_V83.js",
        "/favicon.ico",
        "/index.html",
        "/main-AR3JE4UJ.js",
        "/manifest.webmanifest",
        "/ngsw-worker.js",
        "/safety-worker.js",
        "/styles-TSNORV5H.css",
        "/worker-basic.min.js"
      ],
      "patterns": []
    },
    {
      "name": "assets",
      "installMode": "lazy",
      "updateMode": "prefetch",
      "cacheQueryOptions": {
        "ignoreVary": true
      },
      "urls": [
        "/data/1.0/icons.webp",
        "/data/1.1/icons.webp",
        "/data/1.1e/icons.webp",
        "/data/2.0/icons.webp",
        "/data/aai/icons.webp",
        "/data/bob/icons.webp",
        "/data/bobang/icons.webp",
        "/data/coi/icons.webp",
        "/data/dsp/icons.webp",
        "/data/fay/icons.webp",
        "/data/fdy/icons.webp",
        "/data/ffy/icons.webp",
        "/data/ir3/icons.webp",
        "/data/kr2/icons.webp",
        "/data/kr2sxp/icons.webp",
        "/data/mde/icons.webp",
        "/data/mds/icons.webp",
        "/data/mtm/icons.webp",
        "/data/nls/icons.webp",
        "/data/ows/icons.webp",
        "/data/pys/icons.webp",
        "/data/pysalf/icons.webp",
        "/data/sea/icons.webp",
        "/data/sfy/icons.webp",
        "/data/sky/icons.webp",
        "/data/spa/icons.webp",
        "/data/str/icons.webp",
        "/data/sxp/icons.webp",
        "/data/tta/icons.webp",
        "/factoriolab-animate.webp",
        "/factoriolab.webp",
        "/icons/icon-128x128.png",
        "/icons/icon-144x144.png",
        "/icons/icon-152x152.png",
        "/icons/icon-192x192.png",
        "/icons/icon-384x384.png",
        "/icons/icon-512x512.png",
        "/icons/icon-72x72.png",
        "/icons/icon-96x96.png",
        "/icons/icons.webp"
      ],
      "patterns": []
    }
  ],
  "dataGroups": [],
  "hashTable": {
    "/chunk-BTqFL-W6.js": "7cee609bd132828b1c27036f36798918abbca14b",
    "/chunk-BkuTk0YZ.js": "52869b67131f92a0598a4d1eafb6e8188b12f87e",
    "/chunk-Bootd70g.js": "634927b6aac666b272c855676d118fa403caff39",
    "/chunk-C0_8OVSk.js": "9006ed2d2a568bd2842e81ac57736d84a809d29a",
    "/chunk-C0bSLCE5.js": "76014a14b0f6cef6fd981c8dcf69c82d4acb9abb",
    "/chunk-C8VUx5tz.js": "53a673b987f3dfc73d2fc97c89cec7b1b2ab2c0d",
    "/chunk-C9JAyV3O.js": "2c317c50f6a36ef52ec61c09a6bd119922a6bf51",
    "/chunk-CZijNNNV.js": "9d8c3469c4ded8633e9cecc86cd94352d75ed004",
    "/chunk-CazVxgio.js": "f5714239c54e3f0ef16488114c563f2762af62c8",
    "/chunk-Cn5-OQAh.js": "72e72e6d96f4ef4209e1f697efd5e7220929b822",
    "/chunk-CpJtyA6b.js": "9e0634c46039bfa3bd927897f1393a430335f098",
    "/chunk-CqoeM8zE.js": "f8b94b742dedd03ce08c5e19422ca56eb51bf1d4",
    "/chunk-CsXf57FG.js": "dd8d4b4c3325b3de608f793b50e9c686827b4fb6",
    "/chunk-Cx73aAe6.js": "052082a3bffdd30b460250ebdbb64f7bd94ce17b",
    "/chunk-Cz3iYWRY.js": "abbee58932af018e8b835263f85f3c1fab2c261a",
    "/chunk-DG5sq5fk.js": "07250eafd1a57c4b301cddb2ff68ed73807c2ba8",
    "/chunk-DPXY-fVQ.js": "b660e134961194d22d4e1fd1947b01e8f524bb64",
    "/chunk-Dfp82Ogv.js": "55139a9b32761faa74880fedb9627bfc4b96c97b",
    "/chunk-Dta_GJj0.js": "aea33b98dbd0fa0a5aaa73d9e758e93f07e86ae1",
    "/chunk-HUV4_jLT.js": "d3dbd5762a1d3f7e491a15bdd0366b73dbc9a992",
    "/chunk-Khg8wsls.js": "be286b75234dc44b78ceb649d1a7c0e8bbc4e331",
    "/chunk-PzpOrqc7.js": "ea2a1f1ee58f3bae06e9c704a6b13b046e5ecc34",
    "/chunk-fyBPlGZN.js": "6c58e7542ac290e247165e01bb5972af1908499c",
    "/chunk-kzr3_V83.js": "9a5c1c329f456fd73b55a3b3af014d1bff3474b4",
    "/data/1.0/icons.webp": "33ed6a599827c919248ef966249502bc8a2d8305",
    "/data/1.1/icons.webp": "c22aebdfe156f65a85da43c75b60cac7aac7a1b8",
    "/data/1.1e/icons.webp": "c22aebdfe156f65a85da43c75b60cac7aac7a1b8",
    "/data/2.0/icons.webp": "2b87aa740be40ee2a028521587e7d78097eb905f",
    "/data/aai/icons.webp": "58e8cd5d9742e47accd7ad49c024ab118c9b0b3f",
    "/data/bob/icons.webp": "0d1c5a283fb97c5dd2c85d7c63690e462ab76684",
    "/data/bobang/icons.webp": "c1579fafea29df830303b7098e8cbe2a23c68bde",
    "/data/coi/icons.webp": "286fd6efad015d89512b60422cc1c289d68e7f9e",
    "/data/dsp/icons.webp": "78cdffd8f250f81ed98d86a0581cc74f88c6c2ca",
    "/data/fay/icons.webp": "47c03a708cf42c65a851e4e1f3872021f19bc827",
    "/data/fdy/icons.webp": "dc9e66a97c1ab6e3e135d6964618a39ba9bde0cd",
    "/data/ffy/icons.webp": "b2519b9ab89a85975d4c8172adb1c890fd7b5c31",
    "/data/ir3/icons.webp": "e2295e852429c0701a762c46cf6f40f30a5fcf6e",
    "/data/kr2/icons.webp": "180538ae34c563fed857be3b34c58832af043fb2",
    "/data/kr2sxp/icons.webp": "536bb7f5f8ac1e813eb0714559fd0977d0c2d8d2",
    "/data/mde/icons.webp": "d3d66cc3b195d2ef483123278f5fb56253a81d19",
    "/data/mds/icons.webp": "bc09a90cd25324c7249a25eb0bd191ef6a2761ea",
    "/data/mtm/icons.webp": "c7920b1f331b0ada0a696f64367583c5d1cafc4f",
    "/data/nls/icons.webp": "7e832a9bd2d84565876546a297509347172116fe",
    "/data/ows/icons.webp": "b845af5eb4a57e44ad49499472701cb274c99193",
    "/data/pys/icons.webp": "5fe280bd38c90bf8f578c9934c03233091fe4fea",
    "/data/pysalf/icons.webp": "9421e3f493eb9dcd7796b4913425ff700e9b1856",
    "/data/sea/icons.webp": "2e3788500b932d739d40a3848d757b4200a20b33",
    "/data/sfy/icons.webp": "5ceb5475dcf87a1763ed9172df3ae06e63e6c675",
    "/data/sky/icons.webp": "d6e0e0ee4463600349d9fba6c95dd0441c803d03",
    "/data/spa/icons.webp": "232cffb12a0b4ff8bef8758e93b79eb76d5d6e32",
    "/data/str/icons.webp": "c12d6802d8979945097806efbcad34f5cc873c44",
    "/data/sxp/icons.webp": "b0d5a49bf8b7f3d74f39c395fba944b5cfe9f9c5",
    "/data/tta/icons.webp": "62cb48398d0fb286bf6a48d991f826bd406385f5",
    "/factoriolab-animate.webp": "d1b59c47caa2afddeeef0702eb2ea7db13c8cf0b",
    "/factoriolab.webp": "0994ab2d6435fc680f9fe8eca7f59cf3f709f599",
    "/favicon.ico": "b8d26af58388eccd6d21c2118e07f956bcaf0a6a",
    "/icons/icon-128x128.png": "983e77afd570f31ac052b051c3195ad4f868abf6",
    "/icons/icon-144x144.png": "f7ca93fd4ecf6f8c64cb159ca872be67de2dc0b5",
    "/icons/icon-152x152.png": "324e466aa2f678b7cba6627d4107d0f0fdf51c4a",
    "/icons/icon-192x192.png": "dbd517a74cb7fdea1aa16c8b0293286a3703b7b5",
    "/icons/icon-384x384.png": "45060c738e8c04429fa75766215459c644ffe4b1",
    "/icons/icon-512x512.png": "8316392f7ba8787290d81642e3f81981e2e8dc32",
    "/icons/icon-72x72.png": "af772f4d8e1f9d20a1a73cd74875dc44dbe61d1d",
    "/icons/icon-96x96.png": "e2f631847e869a681191485f9273c892eeb4ef09",
    "/icons/icons.webp": "2017a6f92ab1e7da9207dcf11bcb06b2da800242",
    "/index.html": "e052ca0ceb998172847b54deede5d4002cdd2bfd",
    "/main-AR3JE4UJ.js": "ff41130e32e9abf3d3e6cba7310e233ca01188f4",
    "/manifest.webmanifest": "bdd5fd376e4f00202de41aada8e53eabea3db91d",
    "/ngsw-worker.js": "e9b33d212937bace0967b94ff7cca3a9b873ef8d",
    "/safety-worker.js": "3b3c24f5fca13ee61325298c2009282aeef273c7",
    "/styles-TSNORV5H.css": "0ca86b9c0aafab05a12a7c4afee2cccbcd40219c",
    "/worker-basic.min.js": "3b3c24f5fca13ee61325298c2009282aeef273c7"
  },
  "navigationUrls": [
    {
      "positive": true,
      "regex": "^\\/.*$"
    },
    {
      "positive": false,
      "regex": "^\\/(?:.+\\/)?[^/]*\\.[^/]*$"
    },
    {
      "positive": false,
      "regex": "^\\/(?:.+\\/)?[^/]*__[^/]*$"
    },
    {
      "positive": false,
      "regex": "^\\/(?:.+\\/)?[^/]*__[^/]*\\/.*$"
    },
    {
      "positive": false,
      "regex": "^\\/staging$"
    },
    {
      "positive": false,
      "regex": "^\\/staging\\/.*$"
    },
    {
      "positive": false,
      "regex": "^\\/next$"
    },
    {
      "positive": false,
      "regex": "^\\/next\\/.*$"
    },
    {
      "positive": false,
      "regex": "^\\/old$"
    },
    {
      "positive": false,
      "regex": "^\\/old\\/.*$"
    }
  ],
  "navigationRequestStrategy": "performance"
}